{
  "pageProps": {
    "type": "facilities",
    "id": "9c5c7640-b193-11ed-9392-6dc99afb9280",
    "attributes": {
      "name": "Bochum",
      "description": "<p class=\"cs-p\">.</p>",
      "state": "active",
      "visibility": "public",
      "slug": "germany/dortmund/glasfaser-ruhr-bochum",
      "website": "https://www.glasfaser-ruhr.de/",
      "adminNotes": null,
      "premiumUntil": null,
      "certOix2": null,
      "certUptimeMAndO": null,
      "certUptimeConstructed": null,
      "certUptimeOperation": null,
      "certUptimeOperationGrade": null,
      "buildGenType": null,
      "buildGenFloorLoadCap": null,
      "buildGenRaised": null,
      "buildGenLoadingDocs": null,
      "buildGenLeased": null,
      "buildGenCarrierNeutral": null,
      "buildGenSatellitePlat": null,
      "buildSizeGross": null,
      "buildSizeColocationTot": null,
      "buildSizeRoofAva": null,
      "powerGenPue": null,
      "powerGenRackMax": null,
      "powerGenTotal": null,
      "powerUpsType": null,
      "powerGeneratorDuration": null,
      "powerGeneratorRedundancy": null,
      "powerGeneratorUtility": null,
      "colocRackCagedAreas": null,
      "colocSubRacks": "",
      "interMeetme": null,
      "secPhyBulletProof": null,
      "secPhyMantrap": null,
      "secEleCctv": null,
      "secEleCctvBackup": null,
      "secHumanGuard": null,
      "airConfigHumidity": null,
      "airConfigTemp": null,
      "airConfigTempVar": null,
      "airConfigHumidityVar": null,
      "interFiberConn": null,
      "custOffices": null,
      "custBoardRoom": null,
      "custBreakRoom": null,
      "custWifiAccess": null,
      "custSpareParts": null,
      "custMeetingRoom": null,
      "genDistanceToAirport": null,
      "loadingDocSize": null,
      "utilityConnectionRedundancy": null,
      "rackHeight": null,
      "authenticationFactor": null,
      "bioMetric": null,
      "stagingRooms": null,
      "onSiteParking": null,
      "salesPhone": null,
      "salesEmail": null,
      "supportPhone": null,
      "supportEmail": null,
      "dataVerified": null,
      "createdAt": "2023-02-21T02:58:25.000000Z",
      "updatedAt": "2023-02-21T03:02:44.000000Z"
    },
    "relationships": {
      "analyticsCounts": {
        "links": {
          "self": "http://directory-service.us-west-2.cloudscene.com/facilities/9c5c7640-b193-11ed-9392-6dc99afb9280/relationships/analyticsCounts",
          "related": "http://directory-service.us-west-2.cloudscene.com/facilities/9c5c7640-b193-11ed-9392-6dc99afb9280/analyticsCounts"
        }
      },
      "certificationOptions": {
        "links": {
          "self": "http://directory-service.us-west-2.cloudscene.com/facilities/9c5c7640-b193-11ed-9392-6dc99afb9280/relationships/certificationOptions",
          "related": "http://directory-service.us-west-2.cloudscene.com/facilities/9c5c7640-b193-11ed-9392-6dc99afb9280/certificationOptions"
        }
      },
      "changeRequests": {
        "links": {
          "self": "http://directory-service.us-west-2.cloudscene.com/facilities/9c5c7640-b193-11ed-9392-6dc99afb9280/relationships/changeRequests",
          "related": "http://directory-service.us-west-2.cloudscene.com/facilities/9c5c7640-b193-11ed-9392-6dc99afb9280/changeRequests"
        }
      },
      "companyProfile": {
        "data": {
          "type": "companyProfiles",
          "id": "105df430-b193-11ed-bcdc-7b072ecad2df"
        },
        "links": {
          "self": "http://directory-service.us-west-2.cloudscene.com/facilities/9c5c7640-b193-11ed-9392-6dc99afb9280/relationships/companyProfile",
          "related": "http://directory-service.us-west-2.cloudscene.com/facilities/9c5c7640-b193-11ed-9392-6dc99afb9280/companyProfile"
        }
      },
      "facilityTier": {
        "data": null,
        "links": {
          "self": "http://directory-service.us-west-2.cloudscene.com/facilities/9c5c7640-b193-11ed-9392-6dc99afb9280/relationships/facilityTier",
          "related": "http://directory-service.us-west-2.cloudscene.com/facilities/9c5c7640-b193-11ed-9392-6dc99afb9280/facilityTier"
        }
      },
      "fabrics": {
        "links": {
          "self": "http://directory-service.us-west-2.cloudscene.com/facilities/9c5c7640-b193-11ed-9392-6dc99afb9280/relationships/fabrics",
          "related": "http://directory-service.us-west-2.cloudscene.com/facilities/9c5c7640-b193-11ed-9392-6dc99afb9280/fabrics"
        }
      },
      "location": {
        "links": {
          "self": "http://directory-service.us-west-2.cloudscene.com/facilities/9c5c7640-b193-11ed-9392-6dc99afb9280/relationships/location",
          "related": "http://directory-service.us-west-2.cloudscene.com/facilities/9c5c7640-b193-11ed-9392-6dc99afb9280/location"
        }
      },
      "market": {
        "data": {
          "type": "markets",
          "id": "2171b091-9144-11e7-a556-02028ff44134"
        },
        "links": {
          "self": "http://directory-service.us-west-2.cloudscene.com/facilities/9c5c7640-b193-11ed-9392-6dc99afb9280/relationships/market",
          "related": "http://directory-service.us-west-2.cloudscene.com/facilities/9c5c7640-b193-11ed-9392-6dc99afb9280/market"
        }
      },
      "onRamps": {
        "links": {
          "self": "http://directory-service.us-west-2.cloudscene.com/facilities/9c5c7640-b193-11ed-9392-6dc99afb9280/relationships/onRamps",
          "related": "http://directory-service.us-west-2.cloudscene.com/facilities/9c5c7640-b193-11ed-9392-6dc99afb9280/onRamps"
        }
      },
      "pops": {
        "links": {
          "self": "http://directory-service.us-west-2.cloudscene.com/facilities/9c5c7640-b193-11ed-9392-6dc99afb9280/relationships/pops",
          "related": "http://directory-service.us-west-2.cloudscene.com/facilities/9c5c7640-b193-11ed-9392-6dc99afb9280/pops"
        }
      },
      "zone": {
        "data": {
          "type": "zones",
          "id": "2154436c-9144-11e7-a556-02028ff44134"
        },
        "links": {
          "self": "http://directory-service.us-west-2.cloudscene.com/facilities/9c5c7640-b193-11ed-9392-6dc99afb9280/relationships/zone",
          "related": "http://directory-service.us-west-2.cloudscene.com/facilities/9c5c7640-b193-11ed-9392-6dc99afb9280/zone"
        }
      },
      "documents": {
        "data": [],
        "links": {
          "self": "http://directory-service.us-west-2.cloudscene.com/facilities/9c5c7640-b193-11ed-9392-6dc99afb9280/relationships/documents",
          "related": "http://directory-service.us-west-2.cloudscene.com/facilities/9c5c7640-b193-11ed-9392-6dc99afb9280/documents"
        }
      },
      "bannerImages": {
        "data": [],
        "links": {
          "self": "http://directory-service.us-west-2.cloudscene.com/facilities/9c5c7640-b193-11ed-9392-6dc99afb9280/relationships/bannerImages",
          "related": "http://directory-service.us-west-2.cloudscene.com/facilities/9c5c7640-b193-11ed-9392-6dc99afb9280/bannerImages"
        }
      }
    },
    "links": {
      "self": "http://directory-service.us-west-2.cloudscene.com/facilities/9c5c7640-b193-11ed-9392-6dc99afb9280"
    },
    "meta": {
      "links": {
        "related": "http://directory-service.us-west-2.cloudscene.com/facilities/9c5c7640-b193-11ed-9392-6dc99afb9280/related"
      },
      "counts": {
        "pops": 0,
        "onRamps": 0,
        "fabrics": 0
      },
      "premium": false,
      "actions": {
        "all": true
      }
    },
    "provider": {
      "type": "companyProfiles",
      "id": "105df430-b193-11ed-bcdc-7b072ecad2df",
      "attributes": {
        "name": "Glasfaser Ruhr",
        "legalName": "Glasfaser Ruhr",
        "slug": "glasfaser-ruhr",
        "description": "<p class=\"cs-p\">.</p>",
        "logo": "https://directory-service-090921371925-us-west-2-prod.s3-us-west-2.amazonaws.com/logo/ab-184.JPG",
        "website": "https://www.glasfaser-ruhr.de/rechenzentrum/",
        "foundingYear": "2022",
        "companySize": "1",
        "companyType": null,
        "linkedin": null,
        "twitter": null,
        "facebook": null,
        "salesPhone": "0234 960 38 0",
        "salesEmail": "info@glasfaser-ruhr.de",
        "supportPhone": null,
        "supportEmail": null,
        "adminNotes": null,
        "visibility": "public",
        "premiumUntil": null,
        "createdAt": "2023-02-21T02:54:31.000000Z",
        "updatedAt": "2023-02-21T02:55:02.000000Z"
      },
      "relationships": {
        "analyticsCounts": {
          "links": {
            "self": "http://directory-service.us-west-2.cloudscene.com/companyProfiles/105df430-b193-11ed-bcdc-7b072ecad2df/relationships/analyticsCounts",
            "related": "http://directory-service.us-west-2.cloudscene.com/companyProfiles/105df430-b193-11ed-bcdc-7b072ecad2df/analyticsCounts"
          }
        },
        "certificationOptions": {
          "links": {
            "self": "http://directory-service.us-west-2.cloudscene.com/companyProfiles/105df430-b193-11ed-bcdc-7b072ecad2df/relationships/certificationOptions",
            "related": "http://directory-service.us-west-2.cloudscene.com/companyProfiles/105df430-b193-11ed-bcdc-7b072ecad2df/certificationOptions"
          }
        },
        "changeRequests": {
          "links": {
            "self": "http://directory-service.us-west-2.cloudscene.com/companyProfiles/105df430-b193-11ed-bcdc-7b072ecad2df/relationships/changeRequests",
            "related": "http://directory-service.us-west-2.cloudscene.com/companyProfiles/105df430-b193-11ed-bcdc-7b072ecad2df/changeRequests"
          }
        },
        "childCompanyProfiles": {
          "links": {
            "self": "http://directory-service.us-west-2.cloudscene.com/companyProfiles/105df430-b193-11ed-bcdc-7b072ecad2df/relationships/childCompanyProfiles",
            "related": "http://directory-service.us-west-2.cloudscene.com/companyProfiles/105df430-b193-11ed-bcdc-7b072ecad2df/childCompanyProfiles"
          }
        },
        "companyCategories": {
          "links": {
            "self": "http://directory-service.us-west-2.cloudscene.com/companyProfiles/105df430-b193-11ed-bcdc-7b072ecad2df/relationships/companyCategories",
            "related": "http://directory-service.us-west-2.cloudscene.com/companyProfiles/105df430-b193-11ed-bcdc-7b072ecad2df/companyCategories"
          }
        },
        "documents": {
          "links": {
            "self": "http://directory-service.us-west-2.cloudscene.com/companyProfiles/105df430-b193-11ed-bcdc-7b072ecad2df/relationships/documents",
            "related": "http://directory-service.us-west-2.cloudscene.com/companyProfiles/105df430-b193-11ed-bcdc-7b072ecad2df/documents"
          }
        },
        "bannerImages": {
          "links": {
            "self": "http://directory-service.us-west-2.cloudscene.com/companyProfiles/105df430-b193-11ed-bcdc-7b072ecad2df/relationships/bannerImages",
            "related": "http://directory-service.us-west-2.cloudscene.com/companyProfiles/105df430-b193-11ed-bcdc-7b072ecad2df/bannerImages"
          }
        },
        "fabricMemberships": {
          "links": {
            "self": "http://directory-service.us-west-2.cloudscene.com/companyProfiles/105df430-b193-11ed-bcdc-7b072ecad2df/relationships/fabricMemberships",
            "related": "http://directory-service.us-west-2.cloudscene.com/companyProfiles/105df430-b193-11ed-bcdc-7b072ecad2df/fabricMemberships"
          }
        },
        "fabrics": {
          "links": {
            "self": "http://directory-service.us-west-2.cloudscene.com/companyProfiles/105df430-b193-11ed-bcdc-7b072ecad2df/relationships/fabrics",
            "related": "http://directory-service.us-west-2.cloudscene.com/companyProfiles/105df430-b193-11ed-bcdc-7b072ecad2df/fabrics"
          }
        },
        "facilities": {
          "links": {
            "self": "http://directory-service.us-west-2.cloudscene.com/companyProfiles/105df430-b193-11ed-bcdc-7b072ecad2df/relationships/facilities",
            "related": "http://directory-service.us-west-2.cloudscene.com/companyProfiles/105df430-b193-11ed-bcdc-7b072ecad2df/facilities"
          }
        },
        "location": {
          "links": {
            "self": "http://directory-service.us-west-2.cloudscene.com/companyProfiles/105df430-b193-11ed-bcdc-7b072ecad2df/relationships/location",
            "related": "http://directory-service.us-west-2.cloudscene.com/companyProfiles/105df430-b193-11ed-bcdc-7b072ecad2df/location"
          }
        },
        "onRamps": {
          "links": {
            "self": "http://directory-service.us-west-2.cloudscene.com/companyProfiles/105df430-b193-11ed-bcdc-7b072ecad2df/relationships/onRamps",
            "related": "http://directory-service.us-west-2.cloudscene.com/companyProfiles/105df430-b193-11ed-bcdc-7b072ecad2df/onRamps"
          }
        },
        "parentCompanyProfile": {
          "links": {
            "self": "http://directory-service.us-west-2.cloudscene.com/companyProfiles/105df430-b193-11ed-bcdc-7b072ecad2df/relationships/parentCompanyProfile",
            "related": "http://directory-service.us-west-2.cloudscene.com/companyProfiles/105df430-b193-11ed-bcdc-7b072ecad2df/parentCompanyProfile"
          }
        },
        "pops": {
          "links": {
            "self": "http://directory-service.us-west-2.cloudscene.com/companyProfiles/105df430-b193-11ed-bcdc-7b072ecad2df/relationships/pops",
            "related": "http://directory-service.us-west-2.cloudscene.com/companyProfiles/105df430-b193-11ed-bcdc-7b072ecad2df/pops"
          }
        },
        "pressReleases": {
          "links": {
            "self": "http://directory-service.us-west-2.cloudscene.com/companyProfiles/105df430-b193-11ed-bcdc-7b072ecad2df/relationships/pressReleases",
            "related": "http://directory-service.us-west-2.cloudscene.com/companyProfiles/105df430-b193-11ed-bcdc-7b072ecad2df/pressReleases"
          }
        },
        "claim": {
          "links": {
            "self": "http://directory-service.us-west-2.cloudscene.com/companyProfiles/105df430-b193-11ed-bcdc-7b072ecad2df/relationships/claim",
            "related": "http://directory-service.us-west-2.cloudscene.com/companyProfiles/105df430-b193-11ed-bcdc-7b072ecad2df/claim"
          }
        }
      },
      "links": {
        "self": "http://directory-service.us-west-2.cloudscene.com/companyProfiles/105df430-b193-11ed-bcdc-7b072ecad2df"
      },
      "meta": {
        "links": {
          "related": "http://directory-service.us-west-2.cloudscene.com/companyProfiles/105df430-b193-11ed-bcdc-7b072ecad2df/related"
        },
        "counts": {
          "pops": 2,
          "facilities": 2,
          "onRamps": 0,
          "fabrics": 0
        },
        "premium": false,
        "reviews": {
          "overall": 0,
          "customerService": 0,
          "stars": 0,
          "renew": 0,
          "count": 0,
          "score": 0
        },
        "actions": {
          "all": true
        }
      }
    },
    "zone": {
      "type": "zones",
      "id": "2154436c-9144-11e7-a556-02028ff44134",
      "attributes": {
        "name": "Germany",
        "description": "A highly developed market, Germany is considered the financial powerhouse of the European Union. Whilst the country's capital is Berlin, the undisputed digital capital is the western city of Frankfurt which is the #1 ranked German market on Cloudscene based on data center density. The country as a whole has rapidly modernized with advanced technology driving its place as one of Europe’s largest telecom markets.",
        "slug": "data-centers-in-germany/all",
        "iso": "DE",
        "lat": "51.165691",
        "lon": "10.451526",
        "createdAt": "2021-05-14T06:03:59.000000Z",
        "updatedAt": "2021-05-14T06:03:59.000000Z"
      },
      "relationships": {
        "companyProfiles": {
          "links": {
            "related": "http://directory-service.us-west-2.cloudscene.com/zones/2154436c-9144-11e7-a556-02028ff44134/companyProfiles"
          }
        },
        "fabrics": {
          "links": {
            "related": "http://directory-service.us-west-2.cloudscene.com/zones/2154436c-9144-11e7-a556-02028ff44134/fabrics"
          }
        },
        "facilities": {
          "links": {
            "self": "http://directory-service.us-west-2.cloudscene.com/zones/2154436c-9144-11e7-a556-02028ff44134/relationships/facilities",
            "related": "http://directory-service.us-west-2.cloudscene.com/zones/2154436c-9144-11e7-a556-02028ff44134/facilities"
          }
        },
        "markets": {
          "links": {
            "self": "http://directory-service.us-west-2.cloudscene.com/zones/2154436c-9144-11e7-a556-02028ff44134/relationships/markets",
            "related": "http://directory-service.us-west-2.cloudscene.com/zones/2154436c-9144-11e7-a556-02028ff44134/markets"
          }
        },
        "regions": {
          "links": {
            "self": "http://directory-service.us-west-2.cloudscene.com/zones/2154436c-9144-11e7-a556-02028ff44134/relationships/regions",
            "related": "http://directory-service.us-west-2.cloudscene.com/zones/2154436c-9144-11e7-a556-02028ff44134/regions"
          }
        }
      },
      "meta": {
        "links": {
          "related": "http://directory-service.us-west-2.cloudscene.com/zones/2154436c-9144-11e7-a556-02028ff44134/related"
        },
        "counts": {
          "pops": 3481,
          "facilities": 529,
          "fabrics": 43,
          "markets": 17,
          "providers": 943
        }
      }
    },
    "market": {
      "type": "markets",
      "id": "2171b091-9144-11e7-a556-02028ff44134",
      "attributes": {
        "name": "Dortmund",
        "slug": "data-centers-in-germany/dortmund",
        "createdAt": "2021-05-14T06:16:26.000000Z",
        "updatedAt": "2021-05-14T06:16:26.000000Z"
      },
      "relationships": {
        "companyProfiles": {
          "links": {
            "related": "http://directory-service.us-west-2.cloudscene.com/markets/2171b091-9144-11e7-a556-02028ff44134/companyProfiles"
          }
        },
        "fabrics": {
          "links": {
            "related": "http://directory-service.us-west-2.cloudscene.com/markets/2171b091-9144-11e7-a556-02028ff44134/fabrics"
          }
        },
        "facilities": {
          "links": {
            "self": "http://directory-service.us-west-2.cloudscene.com/markets/2171b091-9144-11e7-a556-02028ff44134/relationships/facilities",
            "related": "http://directory-service.us-west-2.cloudscene.com/markets/2171b091-9144-11e7-a556-02028ff44134/facilities"
          }
        },
        "zone": {
          "links": {
            "self": "http://directory-service.us-west-2.cloudscene.com/markets/2171b091-9144-11e7-a556-02028ff44134/relationships/zone",
            "related": "http://directory-service.us-west-2.cloudscene.com/markets/2171b091-9144-11e7-a556-02028ff44134/zone"
          }
        }
      },
      "meta": {
        "links": {
          "related": "http://directory-service.us-west-2.cloudscene.com/markets/2171b091-9144-11e7-a556-02028ff44134/related"
        },
        "counts": {
          "pops": 9,
          "facilities": 9,
          "fabrics": 4,
          "providers": 12
        }
      }
    },
    "bannerImages": [],
    "documents": [],
    "tier": null,
    "isClaimed": false
  },
  "__N_SSG": true
}